manderageneral/__init__.py
manderageneral/test/test_manderageneral.py
manderageneral-0.0.1.dist-info/LICENSE
manderageneral-0.0.1.dist-info/METADATA
manderageneral-0.0.1.dist-info/WHEEL
manderageneral-0.0.1.dist-info/top_level.txt
manderageneral-0.0.1.dist-info/RECORD
