Metadata-Version: 2.1
Name: manderageneral
Version: 0.0.1
Summary: Missing description.
Home-page: https://github.com/ManderaGeneral/manderageneral
Author: Rickard "Mandera" Abraham
Author-email: rickard.abraham@gmail.com
License: mit
Platform: UNKNOWN
Classifier: Programming Language :: Python :: 3.8
Classifier: Programming Language :: Python :: 3.9
Classifier: License :: OSI Approved :: MIT License
Classifier: Operating System :: Microsoft :: Windows
Classifier: Operating System :: POSIX :: Linux
Requires-Python: >=3.8, <3.10
License-File: LICENSE
Requires-Dist: generallibrary
